leanium/__init__.py
leanium/leanium.py
leanium-0.1a2.dist-info/LICENSE
leanium-0.1a2.dist-info/METADATA
leanium-0.1a2.dist-info/WHEEL
leanium-0.1a2.dist-info/top_level.txt
leanium-0.1a2.dist-info/RECORD
