Metadata-Version: 2.1
Name: leanium
Version: 0.1a2
Summary: A lean wrapper around Selenium to handle common try, except, else scenarios
Home-page: UNKNOWN
Author: Brenden Hyde
Author-email: UNKNOWN
License: UNKNOWN
Platform: UNKNOWN
Classifier: License :: OSI Approved :: GNU Affero General Public License v3
Requires-Dist: selenium (==3.141.0)
